{
	"Id": "Lootable_00419",
	"IsStatic": true,
	"useGravity": true,
	"randomRotation": false,
	"Position": {
		"x": 0,
		"y": 0,
		"z": 0
	},
	"Rotation": {
		"x": 0,
		"y": 0,
		"z": 0
	},
	"IsGroupPosition": false,
	"GroupPositions": [],
	"Root": "5eb3dcf086f77447365db6fe",
	"Items": [
		{
			"_id": "5eb3dcf086f77447365db6fe",
			"_tpl": "5d6d2b5486f774785c2ba8ea"
		},
		{
			"_id": "5eb3dcf086f77447365db6ff",
			"_tpl": "5751a25924597722c463c472",
			"parentId": "5eb3dcf086f77447365db6fe",
			"slotId": "main",
			"location": {
				"x": 0,
				"y": 0,
				"r": 0
			}
		},
		{
			"_id": "5eb3dcf086f77447365db700",
			"_tpl": "590c5d4b86f774784e1b9c45",
			"parentId": "5eb3dcf086f77447365db6fe",
			"slotId": "main",
			"location": {
				"x": 1,
				"y": 0,
				"r": 0
			}
		},
		{
			"_id": "5eb3dcf086f77447365db701",
			"_tpl": "5af04b6486f774195a3ebb49",
			"parentId": "5eb3dcf086f77447365db6fe",
			"slotId": "main",
			"location": {
				"x": 2,
				"y": 0,
				"r": 0
			}
		}
	]
}