{
	"Id": "Lootable_00247",
	"IsStatic": true,
	"useGravity": true,
	"randomRotation": false,
	"Position": {
		"x": 0,
		"y": 0,
		"z": 0
	},
	"Rotation": {
		"x": 0,
		"y": 0,
		"z": 0
	},
	"IsGroupPosition": false,
	"GroupPositions": [],
	"Root": "5eb3dcf686f774633006a3cb",
	"Items": [
		{
			"_id": "5eb3dcf686f774633006a3cb",
			"_tpl": "5909d7cf86f77470ee57d75a"
		},
		{
			"_id": "5eb3dcf686f774633006a3cc",
			"_tpl": "59f9cabd86f7743a10721f46",
			"parentId": "5eb3dcf686f774633006a3cb",
			"slotId": "main",
			"location": {
				"x": 0,
				"y": 0,
				"r": 0
			}
		},
		{
			"_id": "5eb3dcf686f774633006a3cd",
			"_tpl": "5998517986f7746017232f7e",
			"parentId": "5eb3dcf686f774633006a3cc",
			"slotId": "mod_pistol_grip"
		},
		{
			"_id": "5eb3dcf686f774633006a3ce",
			"_tpl": "599851db86f77467372f0a18",
			"parentId": "5eb3dcf686f774633006a3cc",
			"slotId": "mod_stock"
		},
		{
			"_id": "5eb3dcf686f774633006a3cf",
			"_tpl": "5998529a86f774647f44f421",
			"parentId": "5eb3dcf686f774633006a3cc",
			"slotId": "mod_magazine"
		},
		{
			"_id": "5eb3dcf686f774633006a3d5",
			"_tpl": "56d59d3ad2720bdb418b4577",
			"parentId": "5eb3dcf686f774633006a3cf",
			"slotId": "cartridges",
			"upd": {
				"StackObjectsCount": 3
			}
		},
		{
			"_id": "5eb3dcf686f774633006a3d0",
			"_tpl": "5998598e86f7740b3f498a86",
			"parentId": "5eb3dcf686f774633006a3cc",
			"slotId": "mod_muzzle"
		},
		{
			"_id": "5eb3dcf686f774633006a3d1",
			"_tpl": "59985a8086f77414ec448d1a",
			"parentId": "5eb3dcf686f774633006a3cc",
			"slotId": "mod_reciever"
		},
		{
			"_id": "5eb3dcf686f774633006a3d2",
			"_tpl": "599860e986f7743bb57573a6",
			"parentId": "5eb3dcf686f774633006a3cc",
			"slotId": "mod_sight_rear"
		},
		{
			"_id": "5eb3dcf686f774633006a3d3",
			"_tpl": "59ccd11386f77428f24a488f",
			"parentId": "5eb3dcf686f774633006a3cc",
			"slotId": "mod_gas_block"
		},
		{
			"_id": "5eb3dcf686f774633006a3d4",
			"_tpl": "5648b1504bdc2d9d488b4584",
			"parentId": "5eb3dcf686f774633006a3d3",
			"slotId": "mod_handguard"
		}
	]
}