{
	"Id": "Lootable_00098",
	"IsStatic": true,
	"useGravity": true,
	"randomRotation": false,
	"Position": {
		"x": 0,
		"y": 0,
		"z": 0
	},
	"Rotation": {
		"x": 0,
		"y": 0,
		"z": 0
	},
	"IsGroupPosition": false,
	"GroupPositions": [],
	"Root": "5ec3f47adb7ec26edf3534e6",
	"Items": [
		{
			"_id": "5ec3f47adb7ec26edf3534e6",
			"_tpl": "5909d50c86f774659e6aaebe"
		},
		{
			"_id": "5ec3f47adb7ec26edf3534e7",
			"_tpl": "5d1b313086f77425227d1678",
			"parentId": "5ec3f47adb7ec26edf3534e6",
			"slotId": "main",
			"location": {
				"x": 0,
				"y": 0,
				"r": 0
			}
		},
		{
			"_id": "5ec3f47adb7ec26edf3534e8",
			"_tpl": "57347c5b245977448d35f6e1",
			"parentId": "5ec3f47adb7ec26edf3534e6",
			"slotId": "main",
			"location": {
				"x": 1,
				"y": 0,
				"r": 0
			}
		},
		{
			"_id": "5ec3f47adb7ec26edf3534e9",
			"_tpl": "590c311186f77424d1667482",
			"parentId": "5ec3f47adb7ec26edf3534e6",
			"slotId": "main",
			"location": {
				"x": 2,
				"y": 0,
				"r": 0
			}
		},
		{
			"_id": "5ec3f47adb7ec26edf3534ea",
			"_tpl": "590c2b4386f77425357b6123",
			"parentId": "5ec3f47adb7ec26edf3534e6",
			"slotId": "main",
			"location": {
				"x": 3,
				"y": 0,
				"r": 0
			}
		}
	]
}