{
	"Id": "Lootable_00367",
	"IsStatic": true,
	"useGravity": true,
	"randomRotation": false,
	"Position": {
		"x": 0,
		"y": 0,
		"z": 0
	},
	"Rotation": {
		"x": 0,
		"y": 0,
		"z": 0
	},
	"IsGroupPosition": false,
	"GroupPositions": [],
	"Root": "5eb3dd3c86f77468595b0839",
	"Items": [
		{
			"_id": "5eb3dd3c86f77468595b0839",
			"_tpl": "5909d36d86f774660f0bb900"
		},
		{
			"_id": "5eb3dd3c86f77468595b083a",
			"_tpl": "5e2af51086f7746d3f3c3402",
			"parentId": "5eb3dd3c86f77468595b0839",
			"slotId": "main",
			"location": {
				"x": 0,
				"y": 0,
				"r": 0
			}
		},
		{
			"_id": "5eb3dd3c86f77468595b083b",
			"_tpl": "5e2af51086f7746d3f3c3402",
			"parentId": "5eb3dd3c86f77468595b0839",
			"slotId": "main",
			"location": {
				"x": 1,
				"y": 0,
				"r": 0
			}
		},
		{
			"_id": "5eb3dd3c86f77468595b083c",
			"_tpl": "5448be9a4bdc2dfd2f8b456a",
			"parentId": "5eb3dd3c86f77468595b0839",
			"slotId": "main",
			"location": {
				"x": 2,
				"y": 0,
				"r": 0
			}
		}
	]
}