{
	"Id": "Lootable_00540",
	"IsStatic": true,
	"useGravity": true,
	"randomRotation": false,
	"Position": {
		"x": 0,
		"y": 0,
		"z": 0
	},
	"Rotation": {
		"x": 0,
		"y": 0,
		"z": 0
	},
	"IsGroupPosition": false,
	"GroupPositions": [],
	"Root": "5eb3dd2d86f77468595afd47",
	"Items": [
		{
			"_id": "5eb3dd2d86f77468595afd47",
			"_tpl": "5909d5ef86f77467974efbd8"
		},
		{
			"_id": "5eb3dd2d86f77468595afd48",
			"_tpl": "588226e62459776e3e094af7",
			"parentId": "5eb3dd2d86f77468595afd47",
			"slotId": "main",
			"location": {
				"x": 0,
				"y": 0,
				"r": 0
			}
		},
		{
			"_id": "5eb3dd2d86f77468595afd49",
			"_tpl": "587df583245977373c4f1129",
			"parentId": "5eb3dd2d86f77468595afd47",
			"slotId": "main",
			"location": {
				"x": 1,
				"y": 0,
				"r": 0
			}
		}
	]
}