{
	"Id": "Lootable_00044",
	"IsStatic": true,
	"useGravity": true,
	"randomRotation": false,
	"Position": {
		"x": 0,
		"y": 0,
		"z": 0
	},
	"Rotation": {
		"x": 0,
		"y": 0,
		"z": 0
	},
	"IsGroupPosition": false,
	"GroupPositions": [],
	"Root": "5ec3f45b686b7e2870344249",
	"Items": [
		{
			"_id": "5ec3f45b686b7e2870344249",
			"_tpl": "578f87b7245977356274f2cd"
		},
		{
			"_id": "5ec3f45b686b7e287034424a",
			"_tpl": "5d1b309586f77425227d1676",
			"parentId": "5ec3f45b686b7e2870344249",
			"slotId": "main",
			"location": {
				"x": 0,
				"y": 0,
				"r": 0
			}
		},
		{
			"_id": "5ec3f45b686b7e287034424b",
			"_tpl": "590a3cd386f77436f20848cb",
			"parentId": "5ec3f45b686b7e2870344249",
			"slotId": "main",
			"location": {
				"x": 1,
				"y": 0,
				"r": 0
			}
		}
	]
}