{
	"Id": "Lootable_00042",
	"IsStatic": true,
	"useGravity": true,
	"randomRotation": false,
	"Position": {
		"x": 0,
		"y": 0,
		"z": 0
	},
	"Rotation": {
		"x": 0,
		"y": 0,
		"z": 0
	},
	"IsGroupPosition": false,
	"GroupPositions": [],
	"Root": "5eb3dd0486f7745e034784cd",
	"Items": [
		{
			"_id": "5eb3dd0486f7745e034784cd",
			"_tpl": "578f87ad245977356274f2cc"
		},
		{
			"_id": "5eb3dd0486f7745e034784ce",
			"_tpl": "57616a9e2459773c7a400234",
			"parentId": "5eb3dd0486f7745e034784cd",
			"slotId": "main",
			"location": {
				"x": 0,
				"y": 0,
				"r": 0
			}
		},
		{
			"_id": "5eb3dd0486f7745e034784cf",
			"_tpl": "57ffb0e42459777d047111c5",
			"parentId": "5eb3dd0486f7745e034784cd",
			"slotId": "main",
			"location": {
				"x": 1,
				"y": 0,
				"r": 0
			}
		},
		{
			"_id": "5eb3dd0486f7745e034784d0",
			"_tpl": "58272d7f2459774f6311ddfd",
			"parentId": "5eb3dd0486f7745e034784cd",
			"slotId": "main",
			"location": {
				"x": 3,
				"y": 0,
				"r": 0
			}
		}
	]
}