{
	"Id": "Lootable_00009",
	"IsStatic": true,
	"useGravity": true,
	"randomRotation": false,
	"Position": {
		"x": 0,
		"y": 0,
		"z": 0
	},
	"Rotation": {
		"x": 0,
		"y": 0,
		"z": 0
	},
	"IsGroupPosition": false,
	"GroupPositions": [],
	"Root": "5eb3dd2986f77447365dbe99",
	"Items": [
		{
			"_id": "5eb3dd2986f77447365dbe99",
			"_tpl": "5909d45286f77465a8136dc6"
		},
		{
			"_id": "5eb3dd2986f77447365dbe9a",
			"_tpl": "56dff0bed2720bb0668b4567",
			"parentId": "5eb3dd2986f77447365dbe99",
			"slotId": "main",
			"location": {
				"x": 0,
				"y": 0,
				"r": 0
			},
			"upd": {
				"StackObjectsCount": 7
			}
		},
		{
			"_id": "5eb3dd2986f77447365dbe9b",
			"_tpl": "56dff4a2d2720bbd668b456a",
			"parentId": "5eb3dd2986f77447365dbe99",
			"slotId": "main",
			"location": {
				"x": 1,
				"y": 0,
				"r": 0
			},
			"upd": {
				"StackObjectsCount": 12
			}
		}
	]
}