{
	"Id": "Lootable_00250",
	"IsStatic": true,
	"useGravity": true,
	"randomRotation": false,
	"Position": {
		"x": 0,
		"y": 0,
		"z": 0
	},
	"Rotation": {
		"x": 0,
		"y": 0,
		"z": 0
	},
	"IsGroupPosition": false,
	"GroupPositions": [],
	"Root": "5ec3f4622dfcb75c1633ddd5",
	"Items": [
		{
			"_id": "5ec3f4622dfcb75c1633ddd5",
			"_tpl": "578f87a3245977356274f2cb"
		},
		{
			"_id": "5ec3f4622dfcb75c1633ddd6",
			"_tpl": "5d1c819a86f774771b0acd6c",
			"parentId": "5ec3f4622dfcb75c1633ddd5",
			"slotId": "main",
			"location": {
				"x": 0,
				"y": 0,
				"r": 0
			}
		},
		{
			"_id": "5ec3f4622dfcb75c1633ddd7",
			"_tpl": "5d1b327086f7742525194449",
			"parentId": "5ec3f4622dfcb75c1633ddd5",
			"slotId": "main",
			"location": {
				"x": 2,
				"y": 0,
				"r": 0
			}
		}
	]
}