{
	"Id": "Lootable_00363",
	"IsStatic": true,
	"useGravity": true,
	"randomRotation": false,
	"Position": {
		"x": 0,
		"y": 0,
		"z": 0
	},
	"Rotation": {
		"x": 0,
		"y": 0,
		"z": 0
	},
	"IsGroupPosition": false,
	"GroupPositions": [],
	"Root": "5ec3f4652dfcb75c1633e035",
	"Items": [
		{
			"_id": "5ec3f4652dfcb75c1633e035",
			"_tpl": "5d6d2bb386f774785b07a77a"
		},
		{
			"_id": "5ec3f4652dfcb75c1633e036",
			"_tpl": "57347d3d245977448f7b7f61",
			"parentId": "5ec3f4652dfcb75c1633e035",
			"slotId": "main",
			"location": {
				"x": 0,
				"y": 0,
				"r": 0
			}
		},
		{
			"_id": "5ec3f4652dfcb75c1633e037",
			"_tpl": "5c13cef886f774072e618e82",
			"parentId": "5ec3f4652dfcb75c1633e035",
			"slotId": "main",
			"location": {
				"x": 1,
				"y": 0,
				"r": 0
			}
		},
		{
			"_id": "5ec3f4652dfcb75c1633e038",
			"_tpl": "5448bd6b4bdc2dfc2f8b4569",
			"parentId": "5ec3f4652dfcb75c1633e035",
			"slotId": "main",
			"location": {
				"x": 2,
				"y": 0,
				"r": 1
			}
		},
		{
			"_id": "5ec3f4652dfcb75c1633e039",
			"_tpl": "5448c12b4bdc2d02308b456f",
			"parentId": "5ec3f4652dfcb75c1633e038",
			"slotId": "mod_magazine"
		},
		{
			"_id": "5ec3f4652dfcb75c1633e03a",
			"_tpl": "573719762459775a626ccbc1",
			"parentId": "5ec3f4652dfcb75c1633e039",
			"slotId": "cartridges",
			"upd": {
				"StackObjectsCount": 4
			}
		},
		{
			"_id": "5ec3f4652dfcb75c1633e03b",
			"_tpl": "57347b8b24597737dd42e192",
			"parentId": "5ec3f4652dfcb75c1633e035",
			"slotId": "main",
			"location": {
				"x": 0,
				"y": 1,
				"r": 0
			}
		},
		{
			"_id": "5ec3f4652dfcb75c1633e03c",
			"_tpl": "59e35abd86f7741778269d82",
			"parentId": "5ec3f4652dfcb75c1633e035",
			"slotId": "main",
			"location": {
				"x": 1,
				"y": 1,
				"r": 0
			}
		}
	]
}