{
	"Id": "Lootable_00095",
	"IsStatic": true,
	"useGravity": true,
	"randomRotation": false,
	"Position": {
		"x": 0,
		"y": 0,
		"z": 0
	},
	"Rotation": {
		"x": 0,
		"y": 0,
		"z": 0
	},
	"IsGroupPosition": false,
	"GroupPositions": [],
	"Root": "5eb3dcf786f774017729d598",
	"Items": [
		{
			"_id": "5eb3dcf786f774017729d598",
			"_tpl": "578f87b7245977356274f2cd"
		},
		{
			"_id": "5eb3dcf786f774017729d599",
			"_tpl": "5909e99886f7740c983b9984",
			"parentId": "5eb3dcf786f774017729d598",
			"slotId": "main",
			"location": {
				"x": 0,
				"y": 0,
				"r": 0
			}
		},
		{
			"_id": "5eb3dcf786f774017729d59a",
			"_tpl": "57347b8b24597737dd42e192",
			"parentId": "5eb3dcf786f774017729d598",
			"slotId": "main",
			"location": {
				"x": 1,
				"y": 0,
				"r": 0
			}
		},
		{
			"_id": "5eb3dcf786f774017729d59b",
			"_tpl": "590a358486f77429692b2790",
			"parentId": "5eb3dcf786f774017729d598",
			"slotId": "main",
			"location": {
				"x": 0,
				"y": 1,
				"r": 0
			}
		}
	]
}