{
	"Id": "Lootable_00011",
	"IsStatic": true,
	"useGravity": true,
	"randomRotation": false,
	"Position": {
		"x": 0,
		"y": 0,
		"z": 0
	},
	"Rotation": {
		"x": 0,
		"y": 0,
		"z": 0
	},
	"IsGroupPosition": false,
	"GroupPositions": [],
	"Root": "5eb3dd1086f7745df52fa67b",
	"Items": [
		{
			"_id": "5eb3dd1086f7745df52fa67b",
			"_tpl": "578f87a3245977356274f2cb"
		},
		{
			"_id": "5eb3dd1086f7745df52fa67c",
			"_tpl": "5d40425986f7743185265461",
			"parentId": "5eb3dd1086f7745df52fa67b",
			"slotId": "main",
			"location": {
				"x": 0,
				"y": 0,
				"r": 0
			}
		},
		{
			"_id": "5eb3dd1086f7745df52fa67d",
			"_tpl": "5734781f24597737e04bf32a",
			"parentId": "5eb3dd1086f7745df52fa67b",
			"slotId": "main",
			"location": {
				"x": 1,
				"y": 0,
				"r": 0
			}
		}
	]
}