{
	"Id": "Lootable_00065",
	"IsStatic": true,
	"useGravity": true,
	"randomRotation": false,
	"Position": {
		"x": 0,
		"y": 0,
		"z": 0
	},
	"Rotation": {
		"x": 0,
		"y": 0,
		"z": 0
	},
	"IsGroupPosition": false,
	"GroupPositions": [],
	"Root": "5eb3dd0f86f774633006b625",
	"Items": [
		{
			"_id": "5eb3dd0f86f774633006b625",
			"_tpl": "578f8778245977358849a9b5"
		},
		{
			"_id": "5eb3dd0f86f774633006b626",
			"_tpl": "5a0ee62286f774369454a7ac",
			"parentId": "5eb3dd0f86f774633006b625",
			"slotId": "main",
			"location": {
				"x": 0,
				"y": 0,
				"r": 0
			}
		}
	]
}