{
	"Id": "Lootable_00378",
	"IsStatic": true,
	"useGravity": true,
	"randomRotation": false,
	"Position": {
		"x": 0,
		"y": 0,
		"z": 0
	},
	"Rotation": {
		"x": 0,
		"y": 0,
		"z": 0
	},
	"IsGroupPosition": false,
	"GroupPositions": [],
	"Root": "5eb3dd2286f77457e636425a",
	"Items": [
		{
			"_id": "5eb3dd2286f77457e636425a",
			"_tpl": "5909d7cf86f77470ee57d75a"
		},
		{
			"_id": "5eb3dd2286f77457e636425b",
			"_tpl": "59e6449086f7746c9f75e822",
			"parentId": "5eb3dd2286f77457e636425a",
			"slotId": "main",
			"location": {
				"x": 0,
				"y": 0,
				"r": 0
			}
		}
	]
}