{
	"Id": "Lootable_00148",
	"IsStatic": true,
	"useGravity": true,
	"randomRotation": false,
	"Position": {
		"x": 0,
		"y": 0,
		"z": 0
	},
	"Rotation": {
		"x": 0,
		"y": 0,
		"z": 0
	},
	"IsGroupPosition": false,
	"GroupPositions": [],
	"Root": "5eb3dcf986f774633006a61d",
	"Items": [
		{
			"_id": "5eb3dcf986f774633006a61d",
			"_tpl": "578f87b7245977356274f2cd"
		},
		{
			"_id": "5eb3dcf986f774633006a61e",
			"_tpl": "56742c284bdc2d98058b456d",
			"parentId": "5eb3dcf986f774633006a61d",
			"slotId": "main",
			"location": {
				"x": 0,
				"y": 0,
				"r": 0
			}
		},
		{
			"_id": "5eb3dcf986f774633006a61f",
			"_tpl": "57347cd0245977445a2d6ff1",
			"parentId": "5eb3dcf986f774633006a61d",
			"slotId": "main",
			"location": {
				"x": 1,
				"y": 0,
				"r": 0
			}
		}
	]
}