{
	"Id": "Lootable_00166",
	"IsStatic": true,
	"useGravity": true,
	"randomRotation": false,
	"Position": {
		"x": 0,
		"y": 0,
		"z": 0
	},
	"Rotation": {
		"x": 0,
		"y": 0,
		"z": 0
	},
	"IsGroupPosition": false,
	"GroupPositions": [],
	"Root": "5eb3dd0d86f774633006b464",
	"Items": [
		{
			"_id": "5eb3dd0d86f774633006b464",
			"_tpl": "578f87ad245977356274f2cc"
		},
		{
			"_id": "5eb3dd0d86f774633006b465",
			"_tpl": "58272d7f2459774f6311ddfd",
			"parentId": "5eb3dd0d86f774633006b464",
			"slotId": "main",
			"location": {
				"x": 0,
				"y": 0,
				"r": 0
			}
		}
	]
}